qmail_util/__init__.py
qmail_util/cli.py
qmail_util/exception_handler.py
qmail_util/main.py
qmail_util/shell.py
qmail_util/version.py
qmail_util-0.0.13.dist-info/entry_points.txt
qmail_util-0.0.13.dist-info/LICENSE
qmail_util-0.0.13.dist-info/WHEEL
qmail_util-0.0.13.dist-info/METADATA
qmail_util-0.0.13.dist-info/RECORD
